setup.py
tableau_tools/__init__.py
tableau_tools/logger.py
tableau_tools/logging_methods.py
tableau_tools/rest_tokens_manager.py
tableau_tools/tabcmd.py
tableau_tools/tableau_emailer.py
tableau_tools/tableau_exceptions.py
tableau_tools/tableau_http.py
tableau_tools/tableau_repository.py
tableau_tools/tableau_rest_xml.py
tableau_tools/tableau_server_rest.py
tableau_tools.egg-info/PKG-INFO
tableau_tools.egg-info/SOURCES.txt
tableau_tools.egg-info/dependency_links.txt
tableau_tools.egg-info/requires.txt
tableau_tools.egg-info/top_level.txt
tableau_tools/examples/archive_site.py
tableau_tools/examples/basic_methods.py
tableau_tools/examples/create_site_sample.py
tableau_tools/examples/hyper_api_samples.py
tableau_tools/examples/limited_rest_api_wrapping_tableau_rest_api.py
tableau_tools/examples/modifying_users_immediately_before_sso.py
tableau_tools/examples/move_extracts_from_server_to_server.py
tableau_tools/examples/permissions_auditing.py
tableau_tools/examples/replicate_site_structure_sample.py
tableau_tools/examples/template_publish_sample.py
tableau_tools/examples/test_suite_all_add_update_delete_publish_tableau_server_rest.py
tableau_tools/examples/test_suite_all_querying_tableau_rest_api_connection.py
tableau_tools/examples/test_suite_all_querying_tableau_server_rest.py
tableau_tools/examples/test_suite_tableau_documents.py
tableau_tools/examples/user_sync_sample.py
tableau_tools/tableau_documents/__init__.py
tableau_tools/tableau_documents/hyper_file_generator.py
tableau_tools/tableau_documents/table_relations.py
tableau_tools/tableau_documents/tableau_columns.py
tableau_tools/tableau_documents/tableau_connection.py
tableau_tools/tableau_documents/tableau_datasource.py
tableau_tools/tableau_documents/tableau_document.py
tableau_tools/tableau_documents/tableau_file.py
tableau_tools/tableau_documents/tableau_parameters.py
tableau_tools/tableau_documents/tableau_workbook.py
tableau_tools/tableau_rest_api/__init__.py
tableau_tools/tableau_rest_api/permissions.py
tableau_tools/tableau_rest_api/published_content.py
tableau_tools/tableau_rest_api/rest_json_request.py
tableau_tools/tableau_rest_api/rest_xml_request.py
